nbvv/__init__.py
nbvv/_version.py
nbvv/img_prep.py
nbvv/volume.py
nbvv-1.6.2.dist-info/METADATA
nbvv-1.6.2.dist-info/WHEEL
nbvv-1.6.2.dist-info/licenses/AUTHORS.md
nbvv-1.6.2.dist-info/licenses/LICENSE
nbvv-1.6.2.dist-info/RECORD
