Metadata-Version: 2.1
Name: nbvv
Version: 1.6.2
Summary: Interactive volumetric voxel viewing
Project-URL: Homepage, https://github.com/allen-cell-animated/nbvv
Author-email: AICS <danielt@alleninstitute.org>
License: Allen Institute Software License – This software license is the 2-clause BSD 
License-File: AUTHORS.md
License-File: LICENSE
Keywords: ipython,jupyter,volume rendering,widgets
Classifier: Development Status :: 4 - Beta
Classifier: Framework :: IPython
Classifier: Intended Audience :: Developers
Classifier: Intended Audience :: Science/Research
Classifier: Programming Language :: Python :: 3
Classifier: Programming Language :: Python :: 3.7
Classifier: Programming Language :: Python :: 3.8
Classifier: Programming Language :: Python :: 3.9
Classifier: Programming Language :: Python :: 3.10
Classifier: Topic :: Multimedia :: Graphics
Requires-Dist: ipydatawidgets>=4.3.2
Requires-Dist: ipywidgets>=8.0.4
Requires-Dist: jupyter-packaging>=0.12.3
Requires-Dist: jupyter>=1.0.0
Requires-Dist: jupyterlab>=3.5.2
Requires-Dist: numpy>=1.14.3
Requires-Dist: scikit-image>=0.13.0
Requires-Dist: scipy>=1.0.0
